<?xml version="1.0"?>
<FormTemplate xmlns:xsd="http://www.w3.org/2001/XMLSchema" xmlns:xsi="http://www.w3.org/2001/XMLSchema-instance">
  <mForm>
    <mTable>
      <FormRow>
        <mRows>
          <FormColumn>
            <mBorderLeftWidth>1</mBorderLeftWidth>
            <mBorderTopWidth>1</mBorderTopWidth>
            <mBorderRightWidth>1</mBorderRightWidth>
            <mBorderBottomWidth>1</mBorderBottomWidth>
            <mWidth>3084.75</mWidth>
            <mHeight>20.25</mHeight>
            <mFontSize>16</mFontSize>
            <mTextAlign>-4108</mTextAlign>
            <mValign>-4107</mValign>
            <mFontColor>0</mFontColor>
            <mRowspan>1</mRowspan>
            <mColspan>31</mColspan>
            <mData>高压设备单机电耗报表</mData>
            <mDataType>string</mDataType>
          </FormColumn>
        </mRows>
      </FormRow>
      <FormRow>
        <mRows>
          <FormColumn>
            <mBorderLeftWidth>1</mBorderLeftWidth>
            <mBorderTopWidth>1</mBorderTopWidth>
            <mBorderRightWidth>1</mBorderRightWidth>
            <mBorderBottomWidth>1</mBorderBottomWidth>
            <mWidth>92.25</mWidth>
            <mHeight>40.5</mHeight>
            <mFontSize>11</mFontSize>
            <mTextAlign>-4108</mTextAlign>
            <mValign>-4108</mValign>
            <mFontColor>0</mFontColor>
            <mRowspan>3</mRowspan>
            <mColspan>1</mColspan>
            <mData>时间</mData>
            <mDataType>string</mDataType>
          </FormColumn>
          <FormColumn>
            <mBorderLeftWidth>1</mBorderLeftWidth>
            <mBorderTopWidth>1</mBorderTopWidth>
            <mBorderRightWidth>1</mBorderRightWidth>
            <mBorderBottomWidth>1</mBorderBottomWidth>
            <mWidth>498.75</mWidth>
            <mHeight>13.5</mHeight>
            <mFontSize>11</mFontSize>
            <mTextAlign>-4108</mTextAlign>
            <mValign>-4107</mValign>
            <mFontColor>0</mFontColor>
            <mRowspan>1</mRowspan>
            <mColspan>5</mColspan>
            <mData>生料</mData>
            <mDataType>string</mDataType>
          </FormColumn>
          <FormColumn>
            <mBorderLeftWidth>1</mBorderLeftWidth>
            <mBorderTopWidth>1</mBorderTopWidth>
            <mBorderRightWidth>1</mBorderRightWidth>
            <mBorderBottomWidth>1</mBorderBottomWidth>
            <mWidth>1097.25</mWidth>
            <mHeight>13.5</mHeight>
            <mFontSize>11</mFontSize>
            <mTextAlign>-4108</mTextAlign>
            <mValign>-4107</mValign>
            <mFontColor>0</mFontColor>
            <mRowspan>1</mRowspan>
            <mColspan>11</mColspan>
            <mData>熟料</mData>
            <mDataType>string</mDataType>
          </FormColumn>
          <FormColumn>
            <mBorderLeftWidth>1</mBorderLeftWidth>
            <mBorderTopWidth>1</mBorderTopWidth>
            <mBorderRightWidth>1</mBorderRightWidth>
            <mBorderBottomWidth>1</mBorderBottomWidth>
            <mWidth>1396.5</mWidth>
            <mHeight>13.5</mHeight>
            <mFontSize>11</mFontSize>
            <mTextAlign>-4108</mTextAlign>
            <mValign>-4107</mValign>
            <mFontColor>0</mFontColor>
            <mRowspan>1</mRowspan>
            <mColspan>14</mColspan>
            <mData>制成</mData>
            <mDataType>string</mDataType>
          </FormColumn>
        </mRows>
      </FormRow>
      <FormRow>
        <mRows>
          <FormColumn>
            <mBorderLeftWidth>1</mBorderLeftWidth>
            <mBorderTopWidth>1</mBorderTopWidth>
            <mBorderRightWidth>1</mBorderRightWidth>
            <mBorderBottomWidth>1</mBorderBottomWidth>
            <mWidth>99.75</mWidth>
            <mHeight>27</mHeight>
            <mFontSize>11</mFontSize>
            <mTextAlign>-4108</mTextAlign>
            <mValign>-4108</mValign>
            <mFontColor>0</mFontColor>
            <mRowspan>2</mRowspan>
            <mColspan>1</mColspan>
            <mData>原料处理</mData>
            <mDataType>string</mDataType>
          </FormColumn>
          <FormColumn>
            <mBorderLeftWidth>1</mBorderLeftWidth>
            <mBorderTopWidth>1</mBorderTopWidth>
            <mBorderRightWidth>1</mBorderRightWidth>
            <mBorderBottomWidth>1</mBorderBottomWidth>
            <mWidth>99.75</mWidth>
            <mHeight>27</mHeight>
            <mFontSize>11</mFontSize>
            <mTextAlign>-4108</mTextAlign>
            <mValign>-4108</mValign>
            <mFontColor>0</mFontColor>
            <mRowspan>2</mRowspan>
            <mColspan>1</mColspan>
            <mData>原料粉磨辅机设备</mData>
            <mDataType>string</mDataType>
          </FormColumn>
          <FormColumn>
            <mBorderLeftWidth>1</mBorderLeftWidth>
            <mBorderTopWidth>1</mBorderTopWidth>
            <mBorderRightWidth>1</mBorderRightWidth>
            <mBorderBottomWidth>1</mBorderBottomWidth>
            <mWidth>99.75</mWidth>
            <mHeight>27</mHeight>
            <mFontSize>11</mFontSize>
            <mTextAlign>-4108</mTextAlign>
            <mValign>-4108</mValign>
            <mFontColor>0</mFontColor>
            <mRowspan>2</mRowspan>
            <mColspan>1</mColspan>
            <mData>原料立磨主电机</mData>
            <mDataType>string</mDataType>
          </FormColumn>
          <FormColumn>
            <mBorderLeftWidth>1</mBorderLeftWidth>
            <mBorderTopWidth>1</mBorderTopWidth>
            <mBorderRightWidth>1</mBorderRightWidth>
            <mBorderBottomWidth>1</mBorderBottomWidth>
            <mWidth>99.75</mWidth>
            <mHeight>27</mHeight>
            <mFontSize>11</mFontSize>
            <mTextAlign>-4108</mTextAlign>
            <mValign>-4108</mValign>
            <mFontColor>0</mFontColor>
            <mRowspan>2</mRowspan>
            <mColspan>1</mColspan>
            <mData>原料立磨循环风机</mData>
            <mDataType>string</mDataType>
          </FormColumn>
          <FormColumn>
            <mBorderLeftWidth>1</mBorderLeftWidth>
            <mBorderTopWidth>1</mBorderTopWidth>
            <mBorderRightWidth>1</mBorderRightWidth>
            <mBorderBottomWidth>1</mBorderBottomWidth>
            <mWidth>99.75</mWidth>
            <mHeight>27</mHeight>
            <mFontSize>11</mFontSize>
            <mTextAlign>-4108</mTextAlign>
            <mValign>-4108</mValign>
            <mFontColor>0</mFontColor>
            <mRowspan>2</mRowspan>
            <mColspan>1</mColspan>
            <mData>合 计</mData>
            <mDataType>string</mDataType>
          </FormColumn>
          <FormColumn>
            <mBorderLeftWidth>1</mBorderLeftWidth>
            <mBorderTopWidth>1</mBorderTopWidth>
            <mBorderRightWidth>1</mBorderRightWidth>
            <mBorderBottomWidth>1</mBorderBottomWidth>
            <mWidth>99.75</mWidth>
            <mHeight>27</mHeight>
            <mFontSize>11</mFontSize>
            <mTextAlign>-4108</mTextAlign>
            <mValign>-4108</mValign>
            <mFontColor>0</mFontColor>
            <mRowspan>2</mRowspan>
            <mColspan>1</mColspan>
            <mData>窑尾辅机</mData>
            <mDataType>string</mDataType>
          </FormColumn>
          <FormColumn>
            <mBorderLeftWidth>1</mBorderLeftWidth>
            <mBorderTopWidth>1</mBorderTopWidth>
            <mBorderRightWidth>1</mBorderRightWidth>
            <mBorderBottomWidth>1</mBorderBottomWidth>
            <mWidth>99.75</mWidth>
            <mHeight>27</mHeight>
            <mFontSize>11</mFontSize>
            <mTextAlign>-4108</mTextAlign>
            <mValign>-4108</mValign>
            <mFontColor>0</mFontColor>
            <mRowspan>2</mRowspan>
            <mColspan>1</mColspan>
            <mData>窑主机</mData>
            <mDataType>string</mDataType>
          </FormColumn>
          <FormColumn>
            <mBorderLeftWidth>1</mBorderLeftWidth>
            <mBorderTopWidth>1</mBorderTopWidth>
            <mBorderRightWidth>1</mBorderRightWidth>
            <mBorderBottomWidth>1</mBorderBottomWidth>
            <mWidth>99.75</mWidth>
            <mHeight>27</mHeight>
            <mFontSize>11</mFontSize>
            <mTextAlign>-4108</mTextAlign>
            <mValign>-4108</mValign>
            <mFontColor>0</mFontColor>
            <mRowspan>2</mRowspan>
            <mColspan>1</mColspan>
            <mData>高温风机</mData>
            <mDataType>string</mDataType>
          </FormColumn>
          <FormColumn>
            <mBorderLeftWidth>1</mBorderLeftWidth>
            <mBorderTopWidth>1</mBorderTopWidth>
            <mBorderRightWidth>1</mBorderRightWidth>
            <mBorderBottomWidth>1</mBorderBottomWidth>
            <mWidth>99.75</mWidth>
            <mHeight>27</mHeight>
            <mFontSize>11</mFontSize>
            <mTextAlign>-4108</mTextAlign>
            <mValign>-4108</mValign>
            <mFontColor>0</mFontColor>
            <mRowspan>2</mRowspan>
            <mColspan>1</mColspan>
            <mData>尾排风机</mData>
            <mDataType>string</mDataType>
          </FormColumn>
          <FormColumn>
            <mBorderLeftWidth>1</mBorderLeftWidth>
            <mBorderTopWidth>1</mBorderTopWidth>
            <mBorderRightWidth>1</mBorderRightWidth>
            <mBorderBottomWidth>1</mBorderBottomWidth>
            <mWidth>99.75</mWidth>
            <mHeight>27</mHeight>
            <mFontSize>11</mFontSize>
            <mTextAlign>-4108</mTextAlign>
            <mValign>-4108</mValign>
            <mFontColor>0</mFontColor>
            <mRowspan>2</mRowspan>
            <mColspan>1</mColspan>
            <mData>窑头排风机</mData>
            <mDataType>string</mDataType>
          </FormColumn>
          <FormColumn>
            <mBorderLeftWidth>1</mBorderLeftWidth>
            <mBorderTopWidth>1</mBorderTopWidth>
            <mBorderRightWidth>1</mBorderRightWidth>
            <mBorderBottomWidth>1</mBorderBottomWidth>
            <mWidth>99.75</mWidth>
            <mHeight>27</mHeight>
            <mFontSize>11</mFontSize>
            <mTextAlign>-4108</mTextAlign>
            <mValign>-4108</mValign>
            <mFontColor>0</mFontColor>
            <mRowspan>2</mRowspan>
            <mColspan>1</mColspan>
            <mData>煤磨主电机</mData>
            <mDataType>string</mDataType>
          </FormColumn>
          <FormColumn>
            <mBorderLeftWidth>1</mBorderLeftWidth>
            <mBorderTopWidth>1</mBorderTopWidth>
            <mBorderRightWidth>1</mBorderRightWidth>
            <mBorderBottomWidth>1</mBorderBottomWidth>
            <mWidth>99.75</mWidth>
            <mHeight>27</mHeight>
            <mFontSize>11</mFontSize>
            <mTextAlign>-4108</mTextAlign>
            <mValign>-4108</mValign>
            <mFontColor>0</mFontColor>
            <mRowspan>2</mRowspan>
            <mColspan>1</mColspan>
            <mData>煤磨排风机</mData>
            <mDataType>string</mDataType>
          </FormColumn>
          <FormColumn>
            <mBorderLeftWidth>1</mBorderLeftWidth>
            <mBorderTopWidth>1</mBorderTopWidth>
            <mBorderRightWidth>1</mBorderRightWidth>
            <mBorderBottomWidth>1</mBorderBottomWidth>
            <mWidth>99.75</mWidth>
            <mHeight>27</mHeight>
            <mFontSize>11</mFontSize>
            <mTextAlign>-4108</mTextAlign>
            <mValign>-4108</mValign>
            <mFontColor>0</mFontColor>
            <mRowspan>2</mRowspan>
            <mColspan>1</mColspan>
            <mData>窑头1#辅机设备</mData>
            <mDataType>string</mDataType>
          </FormColumn>
          <FormColumn>
            <mBorderLeftWidth>1</mBorderLeftWidth>
            <mBorderTopWidth>1</mBorderTopWidth>
            <mBorderRightWidth>1</mBorderRightWidth>
            <mBorderBottomWidth>1</mBorderBottomWidth>
            <mWidth>99.75</mWidth>
            <mHeight>27</mHeight>
            <mFontSize>11</mFontSize>
            <mTextAlign>-4108</mTextAlign>
            <mValign>-4108</mValign>
            <mFontColor>0</mFontColor>
            <mRowspan>2</mRowspan>
            <mColspan>1</mColspan>
            <mData>窑头2#辅机设备</mData>
            <mDataType>string</mDataType>
          </FormColumn>
          <FormColumn>
            <mBorderLeftWidth>1</mBorderLeftWidth>
            <mBorderTopWidth>1</mBorderTopWidth>
            <mBorderRightWidth>1</mBorderRightWidth>
            <mBorderBottomWidth>1</mBorderBottomWidth>
            <mWidth>99.75</mWidth>
            <mHeight>27</mHeight>
            <mFontSize>11</mFontSize>
            <mTextAlign>-4108</mTextAlign>
            <mValign>-4108</mValign>
            <mFontColor>0</mFontColor>
            <mRowspan>2</mRowspan>
            <mColspan>1</mColspan>
            <mData>窑头3#辅机设备</mData>
            <mDataType>string</mDataType>
          </FormColumn>
          <FormColumn>
            <mBorderLeftWidth>1</mBorderLeftWidth>
            <mBorderTopWidth>1</mBorderTopWidth>
            <mBorderRightWidth>1</mBorderRightWidth>
            <mBorderBottomWidth>1</mBorderBottomWidth>
            <mWidth>99.75</mWidth>
            <mHeight>27</mHeight>
            <mFontSize>11</mFontSize>
            <mTextAlign>-4108</mTextAlign>
            <mValign>-4108</mValign>
            <mFontColor>0</mFontColor>
            <mRowspan>2</mRowspan>
            <mColspan>1</mColspan>
            <mData>合 计</mData>
            <mDataType>string</mDataType>
          </FormColumn>
          <FormColumn>
            <mBorderLeftWidth>1</mBorderLeftWidth>
            <mBorderTopWidth>1</mBorderTopWidth>
            <mBorderRightWidth>1</mBorderRightWidth>
            <mBorderBottomWidth>1</mBorderBottomWidth>
            <mWidth>698.25</mWidth>
            <mHeight>13.5</mHeight>
            <mFontSize>11</mFontSize>
            <mTextAlign>-4108</mTextAlign>
            <mValign>-4107</mValign>
            <mFontColor>0</mFontColor>
            <mRowspan>1</mRowspan>
            <mColspan>7</mColspan>
            <mData>1#水泥磨</mData>
            <mDataType>string</mDataType>
          </FormColumn>
          <FormColumn>
            <mBorderLeftWidth>1</mBorderLeftWidth>
            <mBorderTopWidth>1</mBorderTopWidth>
            <mBorderRightWidth>1</mBorderRightWidth>
            <mBorderBottomWidth>1</mBorderBottomWidth>
            <mWidth>698.25</mWidth>
            <mHeight>13.5</mHeight>
            <mFontSize>11</mFontSize>
            <mTextAlign>-4108</mTextAlign>
            <mValign>-4107</mValign>
            <mFontColor>0</mFontColor>
            <mRowspan>1</mRowspan>
            <mColspan>7</mColspan>
            <mData>2#水泥磨</mData>
            <mDataType>string</mDataType>
          </FormColumn>
        </mRows>
      </FormRow>
      <FormRow>
        <mRows>
          <FormColumn>
            <mBorderLeftWidth>1</mBorderLeftWidth>
            <mBorderTopWidth>1</mBorderTopWidth>
            <mBorderRightWidth>1</mBorderRightWidth>
            <mBorderBottomWidth>1</mBorderBottomWidth>
            <mWidth>99.75</mWidth>
            <mHeight>13.5</mHeight>
            <mFontSize>11</mFontSize>
            <mTextAlign>1</mTextAlign>
            <mValign>-4107</mValign>
            <mFontColor>0</mFontColor>
            <mRowspan>1</mRowspan>
            <mColspan>1</mColspan>
            <mData>主电机</mData>
            <mDataType>string</mDataType>
          </FormColumn>
          <FormColumn>
            <mBorderLeftWidth>1</mBorderLeftWidth>
            <mBorderTopWidth>1</mBorderTopWidth>
            <mBorderRightWidth>1</mBorderRightWidth>
            <mBorderBottomWidth>1</mBorderBottomWidth>
            <mWidth>99.75</mWidth>
            <mHeight>13.5</mHeight>
            <mFontSize>11</mFontSize>
            <mTextAlign>1</mTextAlign>
            <mValign>-4107</mValign>
            <mFontColor>0</mFontColor>
            <mRowspan>1</mRowspan>
            <mColspan>1</mColspan>
            <mData>定辊</mData>
            <mDataType>string</mDataType>
          </FormColumn>
          <FormColumn>
            <mBorderLeftWidth>1</mBorderLeftWidth>
            <mBorderTopWidth>1</mBorderTopWidth>
            <mBorderRightWidth>1</mBorderRightWidth>
            <mBorderBottomWidth>1</mBorderBottomWidth>
            <mWidth>99.75</mWidth>
            <mHeight>13.5</mHeight>
            <mFontSize>11</mFontSize>
            <mTextAlign>1</mTextAlign>
            <mValign>-4107</mValign>
            <mFontColor>0</mFontColor>
            <mRowspan>1</mRowspan>
            <mColspan>1</mColspan>
            <mData>动辊</mData>
            <mDataType>string</mDataType>
          </FormColumn>
          <FormColumn>
            <mBorderLeftWidth>1</mBorderLeftWidth>
            <mBorderTopWidth>1</mBorderTopWidth>
            <mBorderRightWidth>1</mBorderRightWidth>
            <mBorderBottomWidth>1</mBorderBottomWidth>
            <mWidth>99.75</mWidth>
            <mHeight>13.5</mHeight>
            <mFontSize>11</mFontSize>
            <mTextAlign>1</mTextAlign>
            <mValign>-4107</mValign>
            <mFontColor>0</mFontColor>
            <mRowspan>1</mRowspan>
            <mColspan>1</mColspan>
            <mData>循环风机</mData>
            <mDataType>string</mDataType>
          </FormColumn>
          <FormColumn>
            <mBorderLeftWidth>1</mBorderLeftWidth>
            <mBorderTopWidth>1</mBorderTopWidth>
            <mBorderRightWidth>1</mBorderRightWidth>
            <mBorderBottomWidth>1</mBorderBottomWidth>
            <mWidth>99.75</mWidth>
            <mHeight>13.5</mHeight>
            <mFontSize>11</mFontSize>
            <mTextAlign>1</mTextAlign>
            <mValign>-4107</mValign>
            <mFontColor>0</mFontColor>
            <mRowspan>1</mRowspan>
            <mColspan>1</mColspan>
            <mData>排风机</mData>
            <mDataType>string</mDataType>
          </FormColumn>
          <FormColumn>
            <mBorderLeftWidth>1</mBorderLeftWidth>
            <mBorderTopWidth>1</mBorderTopWidth>
            <mBorderRightWidth>1</mBorderRightWidth>
            <mBorderBottomWidth>1</mBorderBottomWidth>
            <mWidth>99.75</mWidth>
            <mHeight>13.5</mHeight>
            <mFontSize>11</mFontSize>
            <mTextAlign>1</mTextAlign>
            <mValign>-4107</mValign>
            <mFontColor>0</mFontColor>
            <mRowspan>1</mRowspan>
            <mColspan>1</mColspan>
            <mData>辅机设备</mData>
            <mDataType>string</mDataType>
          </FormColumn>
          <FormColumn>
            <mBorderLeftWidth>1</mBorderLeftWidth>
            <mBorderTopWidth>1</mBorderTopWidth>
            <mBorderRightWidth>1</mBorderRightWidth>
            <mBorderBottomWidth>1</mBorderBottomWidth>
            <mWidth>99.75</mWidth>
            <mHeight>13.5</mHeight>
            <mFontSize>11</mFontSize>
            <mTextAlign>1</mTextAlign>
            <mValign>-4107</mValign>
            <mFontColor>0</mFontColor>
            <mRowspan>1</mRowspan>
            <mColspan>1</mColspan>
            <mData>合 计</mData>
            <mDataType>string</mDataType>
          </FormColumn>
          <FormColumn>
            <mBorderLeftWidth>1</mBorderLeftWidth>
            <mBorderTopWidth>1</mBorderTopWidth>
            <mBorderRightWidth>1</mBorderRightWidth>
            <mBorderBottomWidth>1</mBorderBottomWidth>
            <mWidth>99.75</mWidth>
            <mHeight>13.5</mHeight>
            <mFontSize>11</mFontSize>
            <mTextAlign>1</mTextAlign>
            <mValign>-4107</mValign>
            <mFontColor>0</mFontColor>
            <mRowspan>1</mRowspan>
            <mColspan>1</mColspan>
            <mData>主电机</mData>
            <mDataType>string</mDataType>
          </FormColumn>
          <FormColumn>
            <mBorderLeftWidth>1</mBorderLeftWidth>
            <mBorderTopWidth>1</mBorderTopWidth>
            <mBorderRightWidth>1</mBorderRightWidth>
            <mBorderBottomWidth>1</mBorderBottomWidth>
            <mWidth>99.75</mWidth>
            <mHeight>13.5</mHeight>
            <mFontSize>11</mFontSize>
            <mTextAlign>1</mTextAlign>
            <mValign>-4107</mValign>
            <mFontColor>0</mFontColor>
            <mRowspan>1</mRowspan>
            <mColspan>1</mColspan>
            <mData>定辊</mData>
            <mDataType>string</mDataType>
          </FormColumn>
          <FormColumn>
            <mBorderLeftWidth>1</mBorderLeftWidth>
            <mBorderTopWidth>1</mBorderTopWidth>
            <mBorderRightWidth>1</mBorderRightWidth>
            <mBorderBottomWidth>1</mBorderBottomWidth>
            <mWidth>99.75</mWidth>
            <mHeight>13.5</mHeight>
            <mFontSize>11</mFontSize>
            <mTextAlign>1</mTextAlign>
            <mValign>-4107</mValign>
            <mFontColor>0</mFontColor>
            <mRowspan>1</mRowspan>
            <mColspan>1</mColspan>
            <mData>动辊</mData>
            <mDataType>string</mDataType>
          </FormColumn>
          <FormColumn>
            <mBorderLeftWidth>1</mBorderLeftWidth>
            <mBorderTopWidth>1</mBorderTopWidth>
            <mBorderRightWidth>1</mBorderRightWidth>
            <mBorderBottomWidth>1</mBorderBottomWidth>
            <mWidth>99.75</mWidth>
            <mHeight>13.5</mHeight>
            <mFontSize>11</mFontSize>
            <mTextAlign>1</mTextAlign>
            <mValign>-4107</mValign>
            <mFontColor>0</mFontColor>
            <mRowspan>1</mRowspan>
            <mColspan>1</mColspan>
            <mData>循环风机</mData>
            <mDataType>string</mDataType>
          </FormColumn>
          <FormColumn>
            <mBorderLeftWidth>1</mBorderLeftWidth>
            <mBorderTopWidth>1</mBorderTopWidth>
            <mBorderRightWidth>1</mBorderRightWidth>
            <mBorderBottomWidth>1</mBorderBottomWidth>
            <mWidth>99.75</mWidth>
            <mHeight>13.5</mHeight>
            <mFontSize>11</mFontSize>
            <mTextAlign>1</mTextAlign>
            <mValign>-4107</mValign>
            <mFontColor>0</mFontColor>
            <mRowspan>1</mRowspan>
            <mColspan>1</mColspan>
            <mData>排风机</mData>
            <mDataType>string</mDataType>
          </FormColumn>
          <FormColumn>
            <mBorderLeftWidth>1</mBorderLeftWidth>
            <mBorderTopWidth>1</mBorderTopWidth>
            <mBorderRightWidth>1</mBorderRightWidth>
            <mBorderBottomWidth>1</mBorderBottomWidth>
            <mWidth>99.75</mWidth>
            <mHeight>13.5</mHeight>
            <mFontSize>11</mFontSize>
            <mTextAlign>1</mTextAlign>
            <mValign>-4107</mValign>
            <mFontColor>0</mFontColor>
            <mRowspan>1</mRowspan>
            <mColspan>1</mColspan>
            <mData>辅机设备</mData>
            <mDataType>string</mDataType>
          </FormColumn>
          <FormColumn>
            <mBorderLeftWidth>1</mBorderLeftWidth>
            <mBorderTopWidth>1</mBorderTopWidth>
            <mBorderRightWidth>1</mBorderRightWidth>
            <mBorderBottomWidth>1</mBorderBottomWidth>
            <mWidth>99.75</mWidth>
            <mHeight>13.5</mHeight>
            <mFontSize>11</mFontSize>
            <mTextAlign>1</mTextAlign>
            <mValign>-4107</mValign>
            <mFontColor>0</mFontColor>
            <mRowspan>1</mRowspan>
            <mColspan>1</mColspan>
            <mData>合计</mData>
            <mDataType>string</mDataType>
          </FormColumn>
        </mRows>
      </FormRow>
      <FormRow>
        <mRows>
          <FormColumn>
            <mBorderLeftWidth>0</mBorderLeftWidth>
            <mBorderTopWidth>1</mBorderTopWidth>
            <mBorderRightWidth>0</mBorderRightWidth>
            <mBorderBottomWidth>0</mBorderBottomWidth>
            <mWidth>92.25</mWidth>
            <mHeight>13.5</mHeight>
            <mFontSize>11</mFontSize>
            <mTextAlign>1</mTextAlign>
            <mValign>-4107</mValign>
            <mFontColor>0</mFontColor>
            <mRowspan>1</mRowspan>
            <mColspan>1</mColspan>
            <mData>vDate</mData>
            <mDataType>string</mDataType>
          </FormColumn>
          <FormColumn>
            <mBorderLeftWidth>0</mBorderLeftWidth>
            <mBorderTopWidth>1</mBorderTopWidth>
            <mBorderRightWidth>0</mBorderRightWidth>
            <mBorderBottomWidth>0</mBorderBottomWidth>
            <mWidth>99.75</mWidth>
            <mHeight>13.5</mHeight>
            <mFontSize>11</mFontSize>
            <mTextAlign>1</mTextAlign>
            <mValign>-4107</mValign>
            <mFontColor>0</mFontColor>
            <mRowspan>1</mRowspan>
            <mColspan>1</mColspan>
            <mData>zc_zcshn_zhuzhouc_zhuzhouf_clinker01rawMaterialsDisposeTransformer</mData>
            <mDataType>string</mDataType>
          </FormColumn>
          <FormColumn>
            <mBorderLeftWidth>0</mBorderLeftWidth>
            <mBorderTopWidth>1</mBorderTopWidth>
            <mBorderRightWidth>0</mBorderRightWidth>
            <mBorderBottomWidth>0</mBorderBottomWidth>
            <mWidth>99.75</mWidth>
            <mHeight>13.5</mHeight>
            <mFontSize>11</mFontSize>
            <mTextAlign>1</mTextAlign>
            <mValign>-4107</mValign>
            <mFontColor>0</mFontColor>
            <mRowspan>1</mRowspan>
            <mColspan>1</mColspan>
            <mData>zc_zcshn_zhuzhouc_zhuzhouf_clinker01rawMaterialsMillTransformer</mData>
            <mDataType>string</mDataType>
          </FormColumn>
          <FormColumn>
            <mBorderLeftWidth>0</mBorderLeftWidth>
            <mBorderTopWidth>1</mBorderTopWidth>
            <mBorderRightWidth>0</mBorderRightWidth>
            <mBorderBottomWidth>0</mBorderBottomWidth>
            <mWidth>99.75</mWidth>
            <mHeight>13.5</mHeight>
            <mFontSize>11</mFontSize>
            <mTextAlign>1</mTextAlign>
            <mValign>-4107</mValign>
            <mFontColor>0</mFontColor>
            <mRowspan>1</mRowspan>
            <mColspan>1</mColspan>
            <mData>zc_zcshn_zhuzhouc_zhuzhouf_clinker01rawMealGrindingMainMotor</mData>
            <mDataType>string</mDataType>
          </FormColumn>
          <FormColumn>
            <mBorderLeftWidth>0</mBorderLeftWidth>
            <mBorderTopWidth>1</mBorderTopWidth>
            <mBorderRightWidth>0</mBorderRightWidth>
            <mBorderBottomWidth>0</mBorderBottomWidth>
            <mWidth>99.75</mWidth>
            <mHeight>13.5</mHeight>
            <mFontSize>11</mFontSize>
            <mTextAlign>1</mTextAlign>
            <mValign>-4107</mValign>
            <mFontColor>0</mFontColor>
            <mRowspan>1</mRowspan>
            <mColspan>1</mColspan>
            <mData>zc_zcshn_zhuzhouc_zhuzhouf_clinker01circulatingFan</mData>
            <mDataType>string</mDataType>
          </FormColumn>
          <FormColumn>
            <mBorderLeftWidth>0</mBorderLeftWidth>
            <mBorderTopWidth>1</mBorderTopWidth>
            <mBorderRightWidth>0</mBorderRightWidth>
            <mBorderBottomWidth>0</mBorderBottomWidth>
            <mWidth>99.75</mWidth>
            <mHeight>13.5</mHeight>
            <mFontSize>11</mFontSize>
            <mTextAlign>1</mTextAlign>
            <mValign>-4107</mValign>
            <mFontColor>0</mFontColor>
            <mRowspan>1</mRowspan>
            <mColspan>1</mColspan>
            <mData>rawMaterialsGrindTotal</mData>
            <mDataType>string</mDataType>
          </FormColumn>
          <FormColumn>
            <mBorderLeftWidth>0</mBorderLeftWidth>
            <mBorderTopWidth>1</mBorderTopWidth>
            <mBorderRightWidth>0</mBorderRightWidth>
            <mBorderBottomWidth>0</mBorderBottomWidth>
            <mWidth>99.75</mWidth>
            <mHeight>13.5</mHeight>
            <mFontSize>11</mFontSize>
            <mTextAlign>1</mTextAlign>
            <mValign>-4107</mValign>
            <mFontColor>0</mFontColor>
            <mRowspan>1</mRowspan>
            <mColspan>1</mColspan>
            <mData>zc_zcshn_zhuzhouc_zhuzhouf_clinker01kilnTailTransformer</mData>
            <mDataType>string</mDataType>
          </FormColumn>
          <FormColumn>
            <mBorderLeftWidth>0</mBorderLeftWidth>
            <mBorderTopWidth>1</mBorderTopWidth>
            <mBorderRightWidth>0</mBorderRightWidth>
            <mBorderBottomWidth>0</mBorderBottomWidth>
            <mWidth>99.75</mWidth>
            <mHeight>13.5</mHeight>
            <mFontSize>11</mFontSize>
            <mTextAlign>1</mTextAlign>
            <mValign>-4107</mValign>
            <mFontColor>0</mFontColor>
            <mRowspan>1</mRowspan>
            <mColspan>1</mColspan>
            <mData>zc_zcshn_zhuzhouc_zhuzhouf_clinker01kilnMainMotor</mData>
            <mDataType>string</mDataType>
          </FormColumn>
          <FormColumn>
            <mBorderLeftWidth>0</mBorderLeftWidth>
            <mBorderTopWidth>1</mBorderTopWidth>
            <mBorderRightWidth>0</mBorderRightWidth>
            <mBorderBottomWidth>0</mBorderBottomWidth>
            <mWidth>99.75</mWidth>
            <mHeight>13.5</mHeight>
            <mFontSize>11</mFontSize>
            <mTextAlign>1</mTextAlign>
            <mValign>-4107</mValign>
            <mFontColor>0</mFontColor>
            <mRowspan>1</mRowspan>
            <mColspan>1</mColspan>
            <mData>zc_zcshn_zhuzhouc_zhuzhouf_clinker01highTemperatureFan</mData>
            <mDataType>string</mDataType>
          </FormColumn>
          <FormColumn>
            <mBorderLeftWidth>0</mBorderLeftWidth>
            <mBorderTopWidth>1</mBorderTopWidth>
            <mBorderRightWidth>0</mBorderRightWidth>
            <mBorderBottomWidth>0</mBorderBottomWidth>
            <mWidth>99.75</mWidth>
            <mHeight>13.5</mHeight>
            <mFontSize>11</mFontSize>
            <mTextAlign>1</mTextAlign>
            <mValign>-4107</mValign>
            <mFontColor>0</mFontColor>
            <mRowspan>1</mRowspan>
            <mColspan>1</mColspan>
            <mData>zc_zcshn_zhuzhouc_zhuzhouf_clinker01kilnTailExhaustFan</mData>
            <mDataType>string</mDataType>
          </FormColumn>
          <FormColumn>
            <mBorderLeftWidth>0</mBorderLeftWidth>
            <mBorderTopWidth>1</mBorderTopWidth>
            <mBorderRightWidth>0</mBorderRightWidth>
            <mBorderBottomWidth>0</mBorderBottomWidth>
            <mWidth>99.75</mWidth>
            <mHeight>13.5</mHeight>
            <mFontSize>11</mFontSize>
            <mTextAlign>1</mTextAlign>
            <mValign>-4107</mValign>
            <mFontColor>0</mFontColor>
            <mRowspan>1</mRowspan>
            <mColspan>1</mColspan>
            <mData>zc_zcshn_zhuzhouc_zhuzhouf_clinker01kilnHeadExhaustFan</mData>
            <mDataType>string</mDataType>
          </FormColumn>
          <FormColumn>
            <mBorderLeftWidth>0</mBorderLeftWidth>
            <mBorderTopWidth>1</mBorderTopWidth>
            <mBorderRightWidth>0</mBorderRightWidth>
            <mBorderBottomWidth>0</mBorderBottomWidth>
            <mWidth>99.75</mWidth>
            <mHeight>13.5</mHeight>
            <mFontSize>11</mFontSize>
            <mTextAlign>1</mTextAlign>
            <mValign>-4107</mValign>
            <mFontColor>0</mFontColor>
            <mRowspan>1</mRowspan>
            <mColspan>1</mColspan>
            <mData>zc_zcshn_zhuzhouc_zhuzhouf_clinker01coalMillMainMotor</mData>
            <mDataType>string</mDataType>
          </FormColumn>
          <FormColumn>
            <mBorderLeftWidth>0</mBorderLeftWidth>
            <mBorderTopWidth>1</mBorderTopWidth>
            <mBorderRightWidth>0</mBorderRightWidth>
            <mBorderBottomWidth>0</mBorderBottomWidth>
            <mWidth>99.75</mWidth>
            <mHeight>13.5</mHeight>
            <mFontSize>11</mFontSize>
            <mTextAlign>1</mTextAlign>
            <mValign>-4107</mValign>
            <mFontColor>0</mFontColor>
            <mRowspan>1</mRowspan>
            <mColspan>1</mColspan>
            <mData>zc_zcshn_zhuzhouc_zhuzhouf_clinker01coalMillFan</mData>
            <mDataType>string</mDataType>
          </FormColumn>
          <FormColumn>
            <mBorderLeftWidth>0</mBorderLeftWidth>
            <mBorderTopWidth>1</mBorderTopWidth>
            <mBorderRightWidth>0</mBorderRightWidth>
            <mBorderBottomWidth>0</mBorderBottomWidth>
            <mWidth>99.75</mWidth>
            <mHeight>13.5</mHeight>
            <mFontSize>11</mFontSize>
            <mTextAlign>1</mTextAlign>
            <mValign>-4107</mValign>
            <mFontColor>0</mFontColor>
            <mRowspan>1</mRowspan>
            <mColspan>1</mColspan>
            <mData>zc_zcshn_zhuzhouc_zhuzhouf_clinker01kilnHeadTransformer1</mData>
            <mDataType>string</mDataType>
          </FormColumn>
          <FormColumn>
            <mBorderLeftWidth>0</mBorderLeftWidth>
            <mBorderTopWidth>1</mBorderTopWidth>
            <mBorderRightWidth>0</mBorderRightWidth>
            <mBorderBottomWidth>0</mBorderBottomWidth>
            <mWidth>99.75</mWidth>
            <mHeight>13.5</mHeight>
            <mFontSize>11</mFontSize>
            <mTextAlign>1</mTextAlign>
            <mValign>-4107</mValign>
            <mFontColor>0</mFontColor>
            <mRowspan>1</mRowspan>
            <mColspan>1</mColspan>
            <mData>zc_zcshn_zhuzhouc_zhuzhouf_clinker01kilnHeadTransformer2</mData>
            <mDataType>string</mDataType>
          </FormColumn>
          <FormColumn>
            <mBorderLeftWidth>0</mBorderLeftWidth>
            <mBorderTopWidth>1</mBorderTopWidth>
            <mBorderRightWidth>0</mBorderRightWidth>
            <mBorderBottomWidth>0</mBorderBottomWidth>
            <mWidth>99.75</mWidth>
            <mHeight>13.5</mHeight>
            <mFontSize>11</mFontSize>
            <mTextAlign>1</mTextAlign>
            <mValign>-4107</mValign>
            <mFontColor>0</mFontColor>
            <mRowspan>1</mRowspan>
            <mColspan>1</mColspan>
            <mData>zc_zcshn_zhuzhouc_zhuzhouf_clinker01kilnHeadTransformer3</mData>
            <mDataType>string</mDataType>
          </FormColumn>
          <FormColumn>
            <mBorderLeftWidth>0</mBorderLeftWidth>
            <mBorderTopWidth>1</mBorderTopWidth>
            <mBorderRightWidth>0</mBorderRightWidth>
            <mBorderBottomWidth>0</mBorderBottomWidth>
            <mWidth>99.75</mWidth>
            <mHeight>13.5</mHeight>
            <mFontSize>11</mFontSize>
            <mTextAlign>1</mTextAlign>
            <mValign>-4107</mValign>
            <mFontColor>0</mFontColor>
            <mRowspan>1</mRowspan>
            <mColspan>1</mColspan>
            <mData>zc_zcshn_zhuzhouc_zhuzhouf_clinker01Total</mData>
            <mDataType>string</mDataType>
          </FormColumn>
          <FormColumn>
            <mBorderLeftWidth>0</mBorderLeftWidth>
            <mBorderTopWidth>1</mBorderTopWidth>
            <mBorderRightWidth>0</mBorderRightWidth>
            <mBorderBottomWidth>0</mBorderBottomWidth>
            <mWidth>99.75</mWidth>
            <mHeight>13.5</mHeight>
            <mFontSize>11</mFontSize>
            <mTextAlign>1</mTextAlign>
            <mValign>-4107</mValign>
            <mFontColor>0</mFontColor>
            <mRowspan>1</mRowspan>
            <mColspan>1</mColspan>
            <mData>zc_zcshn_zhuzhouc_zhuzhouf_cementmill01cementMillMainMotor</mData>
            <mDataType>string</mDataType>
          </FormColumn>
          <FormColumn>
            <mBorderLeftWidth>0</mBorderLeftWidth>
            <mBorderTopWidth>1</mBorderTopWidth>
            <mBorderRightWidth>0</mBorderRightWidth>
            <mBorderBottomWidth>0</mBorderBottomWidth>
            <mWidth>99.75</mWidth>
            <mHeight>13.5</mHeight>
            <mFontSize>11</mFontSize>
            <mTextAlign>1</mTextAlign>
            <mValign>-4107</mValign>
            <mFontColor>0</mFontColor>
            <mRowspan>1</mRowspan>
            <mColspan>1</mColspan>
            <mData>zc_zcshn_zhuzhouc_zhuzhouf_cementmill01rollingMachineSettledRoller</mData>
            <mDataType>string</mDataType>
          </FormColumn>
          <FormColumn>
            <mBorderLeftWidth>0</mBorderLeftWidth>
            <mBorderTopWidth>1</mBorderTopWidth>
            <mBorderRightWidth>0</mBorderRightWidth>
            <mBorderBottomWidth>0</mBorderBottomWidth>
            <mWidth>99.75</mWidth>
            <mHeight>13.5</mHeight>
            <mFontSize>11</mFontSize>
            <mTextAlign>1</mTextAlign>
            <mValign>-4107</mValign>
            <mFontColor>0</mFontColor>
            <mRowspan>1</mRowspan>
            <mColspan>1</mColspan>
            <mData>zc_zcshn_zhuzhouc_zhuzhouf_cementmill01rollingMachineActionRoller</mData>
            <mDataType>string</mDataType>
          </FormColumn>
          <FormColumn>
            <mBorderLeftWidth>0</mBorderLeftWidth>
            <mBorderTopWidth>1</mBorderTopWidth>
            <mBorderRightWidth>0</mBorderRightWidth>
            <mBorderBottomWidth>0</mBorderBottomWidth>
            <mWidth>99.75</mWidth>
            <mHeight>13.5</mHeight>
            <mFontSize>11</mFontSize>
            <mTextAlign>1</mTextAlign>
            <mValign>-4107</mValign>
            <mFontColor>0</mFontColor>
            <mRowspan>1</mRowspan>
            <mColspan>1</mColspan>
            <mData>zc_zcshn_zhuzhouc_zhuzhouf_cementmill01circulatingFan</mData>
            <mDataType>string</mDataType>
          </FormColumn>
          <FormColumn>
            <mBorderLeftWidth>0</mBorderLeftWidth>
            <mBorderTopWidth>1</mBorderTopWidth>
            <mBorderRightWidth>0</mBorderRightWidth>
            <mBorderBottomWidth>0</mBorderBottomWidth>
            <mWidth>99.75</mWidth>
            <mHeight>13.5</mHeight>
            <mFontSize>11</mFontSize>
            <mTextAlign>1</mTextAlign>
            <mValign>-4107</mValign>
            <mFontColor>0</mFontColor>
            <mRowspan>1</mRowspan>
            <mColspan>1</mColspan>
            <mData>zc_zcshn_zhuzhouc_zhuzhouf_cementmill01mainExhaustFan</mData>
            <mDataType>string</mDataType>
          </FormColumn>
          <FormColumn>
            <mBorderLeftWidth>0</mBorderLeftWidth>
            <mBorderTopWidth>1</mBorderTopWidth>
            <mBorderRightWidth>0</mBorderRightWidth>
            <mBorderBottomWidth>0</mBorderBottomWidth>
            <mWidth>99.75</mWidth>
            <mHeight>13.5</mHeight>
            <mFontSize>11</mFontSize>
            <mTextAlign>1</mTextAlign>
            <mValign>-4107</mValign>
            <mFontColor>0</mFontColor>
            <mRowspan>1</mRowspan>
            <mColspan>1</mColspan>
            <mData>zc_zcshn_zhuzhouc_zhuzhouf_cementmill01cementmillTransformer</mData>
            <mDataType>string</mDataType>
          </FormColumn>
          <FormColumn>
            <mBorderLeftWidth>0</mBorderLeftWidth>
            <mBorderTopWidth>1</mBorderTopWidth>
            <mBorderRightWidth>0</mBorderRightWidth>
            <mBorderBottomWidth>0</mBorderBottomWidth>
            <mWidth>99.75</mWidth>
            <mHeight>13.5</mHeight>
            <mFontSize>11</mFontSize>
            <mTextAlign>1</mTextAlign>
            <mValign>-4107</mValign>
            <mFontColor>0</mFontColor>
            <mRowspan>1</mRowspan>
            <mColspan>1</mColspan>
            <mData>zc_zcshn_zhuzhouc_zhuzhouf_cementmill01Total</mData>
            <mDataType>string</mDataType>
          </FormColumn>
          <FormColumn>
            <mBorderLeftWidth>0</mBorderLeftWidth>
            <mBorderTopWidth>1</mBorderTopWidth>
            <mBorderRightWidth>0</mBorderRightWidth>
            <mBorderBottomWidth>0</mBorderBottomWidth>
            <mWidth>99.75</mWidth>
            <mHeight>13.5</mHeight>
            <mFontSize>11</mFontSize>
            <mTextAlign>1</mTextAlign>
            <mValign>-4107</mValign>
            <mFontColor>0</mFontColor>
            <mRowspan>1</mRowspan>
            <mColspan>1</mColspan>
            <mData>zc_zcshn_zhuzhouc_zhuzhouf_cementmill02cementMillMainMotor</mData>
            <mDataType>string</mDataType>
          </FormColumn>
          <FormColumn>
            <mBorderLeftWidth>0</mBorderLeftWidth>
            <mBorderTopWidth>1</mBorderTopWidth>
            <mBorderRightWidth>0</mBorderRightWidth>
            <mBorderBottomWidth>0</mBorderBottomWidth>
            <mWidth>99.75</mWidth>
            <mHeight>13.5</mHeight>
            <mFontSize>11</mFontSize>
            <mTextAlign>1</mTextAlign>
            <mValign>-4107</mValign>
            <mFontColor>0</mFontColor>
            <mRowspan>1</mRowspan>
            <mColspan>1</mColspan>
            <mData>zc_zcshn_zhuzhouc_zhuzhouf_cementmill02rollingMachineSettledRoller</mData>
            <mDataType>string</mDataType>
          </FormColumn>
          <FormColumn>
            <mBorderLeftWidth>0</mBorderLeftWidth>
            <mBorderTopWidth>1</mBorderTopWidth>
            <mBorderRightWidth>0</mBorderRightWidth>
            <mBorderBottomWidth>0</mBorderBottomWidth>
            <mWidth>99.75</mWidth>
            <mHeight>13.5</mHeight>
            <mFontSize>11</mFontSize>
            <mTextAlign>1</mTextAlign>
            <mValign>-4107</mValign>
            <mFontColor>0</mFontColor>
            <mRowspan>1</mRowspan>
            <mColspan>1</mColspan>
            <mData>zc_zcshn_zhuzhouc_zhuzhouf_cementmill02rollingMachineActionRoller</mData>
            <mDataType>string</mDataType>
          </FormColumn>
          <FormColumn>
            <mBorderLeftWidth>0</mBorderLeftWidth>
            <mBorderTopWidth>1</mBorderTopWidth>
            <mBorderRightWidth>0</mBorderRightWidth>
            <mBorderBottomWidth>0</mBorderBottomWidth>
            <mWidth>99.75</mWidth>
            <mHeight>13.5</mHeight>
            <mFontSize>11</mFontSize>
            <mTextAlign>1</mTextAlign>
            <mValign>-4107</mValign>
            <mFontColor>0</mFontColor>
            <mRowspan>1</mRowspan>
            <mColspan>1</mColspan>
            <mData>zc_zcshn_zhuzhouc_zhuzhouf_cementmill02circulatingFan</mData>
            <mDataType>string</mDataType>
          </FormColumn>
          <FormColumn>
            <mBorderLeftWidth>0</mBorderLeftWidth>
            <mBorderTopWidth>1</mBorderTopWidth>
            <mBorderRightWidth>0</mBorderRightWidth>
            <mBorderBottomWidth>0</mBorderBottomWidth>
            <mWidth>99.75</mWidth>
            <mHeight>13.5</mHeight>
            <mFontSize>11</mFontSize>
            <mTextAlign>1</mTextAlign>
            <mValign>-4107</mValign>
            <mFontColor>0</mFontColor>
            <mRowspan>1</mRowspan>
            <mColspan>1</mColspan>
            <mData>zc_zcshn_zhuzhouc_zhuzhouf_cementmill02mainExhaustFan</mData>
            <mDataType>string</mDataType>
          </FormColumn>
          <FormColumn>
            <mBorderLeftWidth>0</mBorderLeftWidth>
            <mBorderTopWidth>1</mBorderTopWidth>
            <mBorderRightWidth>0</mBorderRightWidth>
            <mBorderBottomWidth>0</mBorderBottomWidth>
            <mWidth>99.75</mWidth>
            <mHeight>13.5</mHeight>
            <mFontSize>11</mFontSize>
            <mTextAlign>1</mTextAlign>
            <mValign>-4107</mValign>
            <mFontColor>0</mFontColor>
            <mRowspan>1</mRowspan>
            <mColspan>1</mColspan>
            <mData>zc_zcshn_zhuzhouc_zhuzhouf_cementmill02cementmillTransformer</mData>
            <mDataType>string</mDataType>
          </FormColumn>
          <FormColumn>
            <mBorderLeftWidth>0</mBorderLeftWidth>
            <mBorderTopWidth>1</mBorderTopWidth>
            <mBorderRightWidth>0</mBorderRightWidth>
            <mBorderBottomWidth>0</mBorderBottomWidth>
            <mWidth>99.75</mWidth>
            <mHeight>13.5</mHeight>
            <mFontSize>11</mFontSize>
            <mTextAlign>1</mTextAlign>
            <mValign>-4107</mValign>
            <mFontColor>0</mFontColor>
            <mRowspan>1</mRowspan>
            <mColspan>1</mColspan>
            <mData>zc_zcshn_zhuzhouc_zhuzhouf_cementmill02Total</mData>
            <mDataType>string</mDataType>
          </FormColumn>
        </mRows>
      </FormRow>
    </mTable>
  </mForm>
  <mStartDynamicLine>2</mStartDynamicLine>
  <mEndDynamicLine>4</mEndDynamicLine>
  <mHaveColumnFieldLine>true</mHaveColumnFieldLine>
</FormTemplate>